connection_monitor/VERSION
connection_monitor/__init__.py
connection_monitor/__main__.py
connection_monitor/cli.py
connection_monitor/params.py
connection_monitor/utils.py
connection_monitor/domain/__init__.py
connection_monitor/domain/core.py
connection_monitor/domain/model.py
connection_monitor/domain/wifi.py
connection_monitor-0.0.6.dist-info/METADATA
connection_monitor-0.0.6.dist-info/WHEEL
connection_monitor-0.0.6.dist-info/entry_points.txt
connection_monitor-0.0.6.dist-info/top_level.txt
connection_monitor-0.0.6.dist-info/RECORD
