Metadata-Version: 2.1
Name: connection-monitor
Version: 0.0.6
Summary: Connection monitoring utility
Home-page: https://framagit.org/ojob/connection-monitor
Author: Joël Bourgault
Author-email: joel.bourgault@gmail.com
License: UNKNOWN
Platform: UNKNOWN
Classifier: Programming Language :: Python :: 3
Classifier: License :: OSI Approved :: GNU General Public License v3 or later (GPLv3+)
Classifier: Operating System :: OS Independent
Requires-Python: >=3.7
Requires-Dist: bs4
Requires-Dist: click
Requires-Dist: psutil
Requires-Dist: pyyaml
Requires-Dist: requests
